{
  "bulletin": [
    {
      "id": 8,
      "title": "2026　6月14日（日）ログハウスまつり",
      "type": "短期",
      "startDate": "2026.05.19",
      "endDate": "2026.06.15",
      "images": [
        "https://lh3.googleusercontent.com/d/1Gs4S2lHbZkGUitRw9eoyc0ezcjF7zg96"
      ]
    },
    {
      "id": 6,
      "title": "※参加者募集　緑道ハレバレ会さんと行く　渋沢ウォーク",
      "type": "短期",
      "startDate": "2026.05.09",
      "endDate": "2026.06.22",
      "images": [
        "https://lh3.googleusercontent.com/d/17NXYhDAcqjoDTSNvL1_MCU5x1e59cE3s"
      ]
    },
    {
      "id": 7,
      "title": "※参加者募集　「渋沢へなちょこおやじたちの会」トークショー",
      "type": "短期",
      "startDate": "2026.05.09",
      "endDate": "2026.07.05",
      "images": [
        "https://lh3.googleusercontent.com/d/1dk6RlT_oL5k0ijV1v7ymu8TDgTjnbmzq"
      ]
    },
    {
      "id": 4,
      "title": "掲示板テスト４",
      "type": "短期",
      "startDate": "2026.05.02",
      "endDate": "2026.05.28",
      "images": [
        "https://lh3.googleusercontent.com/d/1axwoW1_cZO882_lynbsbljy6AwfgJKIJ"
      ]
    },
    {
      "id": 2,
      "title": "掲示板テスト２",
      "type": "中期",
      "startDate": "2026.05.02",
      "endDate": "2026.07.08",
      "images": [
        "https://lh3.googleusercontent.com/d/15HVODgX4qZlrheLrZFEK53xuurvI54lx"
      ]
    },
    {
      "id": 3,
      "title": "掲示板テスト３",
      "type": "常設",
      "startDate": "",
      "endDate": "",
      "images": [
        "https://lh3.googleusercontent.com/d/1gOVgFTixnleDzdp6iTxnofHXN5s6QS_z",
        "https://lh3.googleusercontent.com/d/1bWDoeZ5BwWoIyGSkjDfpVqeuElcwWs9x"
      ]
    },
    {
      "id": 5,
      "title": "掲示板テスト５",
      "type": "常設",
      "startDate": "",
      "endDate": "",
      "images": [
        "https://lh3.googleusercontent.com/d/1UwiL1bz8FMae-ZreXjmCCdUBR2qzy5to"
      ]
    }
  ]
}